ai_dev_kit/__init__.py
ai_dev_kit/cli.py
ai_dev_kit/py.typed
viper_dev_kit-1.1.0.dist-info/licenses/LICENSE
viper_dev_kit-1.1.0.dist-info/METADATA
viper_dev_kit-1.1.0.dist-info/WHEEL
viper_dev_kit-1.1.0.dist-info/entry_points.txt
viper_dev_kit-1.1.0.dist-info/top_level.txt
viper_dev_kit-1.1.0.dist-info/RECORD
