Metadata-Version: 2.4
Name: viper-dev-kit
Version: 1.1.0
Summary: AI Dev Kit - Universal AI development environment
License-Expression: MIT
Project-URL: Homepage, https://github.com/ViperJuice/ai-dev-kit
Project-URL: Repository, https://github.com/ViperJuice/ai-dev-kit
Requires-Python: >=3.10
License-File: LICENSE
Requires-Dist: mcp>=1.0.0
Requires-Dist: python-dotenv>=1.2.1
Provides-Extra: dev
Requires-Dist: pytest>=7.0.0; extra == "dev"
Requires-Dist: black>=23.0.0; extra == "dev"
Requires-Dist: ruff>=0.1.0; extra == "dev"
Dynamic: license-file
